setup.py
jenkins_jobs_hidden_param.egg-info/PKG-INFO
jenkins_jobs_hidden_param.egg-info/SOURCES.txt
jenkins_jobs_hidden_param.egg-info/dependency_links.txt
jenkins_jobs_hidden_param.egg-info/entry_points.txt
jenkins_jobs_hidden_param.egg-info/top_level.txt
jjb_hidden_param/__init__.py
jjb_hidden_param/hidden_param.py